py_vollib/__init__.py
py_vollib/black/__init__.py
py_vollib/black/implied_volatility.py
py_vollib/black/greeks/__init__.py
py_vollib/black/greeks/analytical.py
py_vollib/black/greeks/numerical.py
py_vollib/black_scholes/__init__.py
py_vollib/black_scholes/implied_volatility.py
py_vollib/black_scholes/greeks/__init__.py
py_vollib/black_scholes/greeks/analytical.py
py_vollib/black_scholes/greeks/numerical.py
py_vollib/black_scholes_merton/__init__.py
py_vollib/black_scholes_merton/implied_volatility.py
py_vollib/black_scholes_merton/greeks/__init__.py
py_vollib/black_scholes_merton/greeks/analytical.py
py_vollib/black_scholes_merton/greeks/numerical.py
py_vollib/helpers/__init__.py
py_vollib/helpers/constants.py
py_vollib/helpers/distributions.py
py_vollib/helpers/doctest_helper.py
py_vollib/helpers/exceptions.py
py_vollib/helpers/numerical_greeks.py
py_vollib/ref_python/__init__.py
py_vollib/ref_python/black/__init__.py
py_vollib/ref_python/black/implied_volatility.py
py_vollib/ref_python/black/greeks/__init__.py
py_vollib/ref_python/black/greeks/analytical.py
py_vollib/ref_python/black/greeks/numerical.py
py_vollib/ref_python/black_scholes/__init__.py
py_vollib/ref_python/black_scholes/implied_volatility.py
py_vollib/ref_python/black_scholes/greeks/__init__.py
py_vollib/ref_python/black_scholes/greeks/analytical.py
py_vollib/ref_python/black_scholes/greeks/numerical.py
py_vollib/ref_python/black_scholes_merton/__init__.py
py_vollib/ref_python/black_scholes_merton/implied_volatility.py
py_vollib/ref_python/black_scholes_merton/greeks/__init__.py
py_vollib/ref_python/black_scholes_merton/greeks/analytical.py
py_vollib/ref_python/black_scholes_merton/greeks/numerical.py
tests/__init__.py
tests/test_all.py
tests/test_black_scholes.py
tests/test_black_scholes_greeks.py
tests/test_black_scholes_merton.py
tests/test_black_scholes_merton_greeks.py
tests/test_utils.py
tests/test_ref_python/__init__.py
tests/test_ref_python/test_ref_python_black_scholes.py
py_vollib_gen-1.0.1.dist-info/LICENSE
py_vollib_gen-1.0.1.dist-info/METADATA
py_vollib_gen-1.0.1.dist-info/WHEEL
py_vollib_gen-1.0.1.dist-info/top_level.txt
py_vollib_gen-1.0.1.dist-info/RECORD
