Metadata-Version: 2.1
Name: py_vollib_gen
Version: 1.0.1
Home-page: 
Maintainer: 
Maintainer-email: 
License: MIT
License-File: LICENSE
Requires-Dist: py-lets-be-rational-gen
Requires-Dist: simplejson
Requires-Dist: numpy
Requires-Dist: pandas
Requires-Dist: scipy
